Workbook

Sheet Sales
A1: Shop Sales Register (October)
A2: Yellow = you type | Green = formula (don't overwrite)
A4: Date | B4: Code | C4: Product | D4: Category | E4: Qty | F4: Price | G4: Amount | H4: Discount | I4: Net | J4: Payment
A5: 46296 | B5: P06 | C5: =VLOOKUP(B5,Products!$A$5:$D$12,2,FALSE) | D5: =_xlfn.XLOOKUP(B5,Products!$A$5:$A$12,Products!$C$5:$C$12,"Not found") | E5: 3 | F5: =VLOOKUP(B5,Products!$A$5:$D$12,4,FALSE) | G5: =E5*F5 | H5: =IF(G5>=20,ROUND(G5*5%,2),0) | I5: =G5-H5 | J5: Credit
A6: 46297 | B6: P01 | C6: =VLOOKUP(B6,Products!$A$5:$D$12,2,FALSE) | D6: =_xlfn.XLOOKUP(B6,Products!$A$5:$A$12,Products!$C$5:$C$12,"Not found") | E6: 2 | F6: =VLOOKUP(B6,Products!$A$5:$D$12,4,FALSE) | G6: =E6*F6 | H6: =IF(G6>=20,ROUND(G6*5%,2),0) | I6: =G6-H6 | J6: Cash
A7: 46298 | B7: P06 | C7: =VLOOKUP(B7,Products!$A$5:$D$12,2,FALSE) | D7: =_xlfn.XLOOKUP(B7,Products!$A$5:$A$12,Products!$C$5:$C$12,"Not found") | E7: 10 | F7: =VLOOKUP(B7,Products!$A$5:$D$12,4,FALSE) | G7: =E7*F7 | H7: =IF(G7>=20,ROUND(G7*5%,2),0) | I7: =G7-H7 | J7: Cash
A8: 46299 | B8: P04 | C8: =VLOOKUP(B8,Products!$A$5:$D$12,2,FALSE) | D8: =_xlfn.XLOOKUP(B8,Products!$A$5:$A$12,Products!$C$5:$C$12,"Not found") | E8: 1 | F8: =VLOOKUP(B8,Products!$A$5:$D$12,4,FALSE) | G8: =E8*F8 | H8: =IF(G8>=20,ROUND(G8*5%,2),0) | I8: =G8-H8 | J8: Cash
A9: 46300 | B9: P07 | C9: =VLOOKUP(B9,Products!$A$5:$D$12,2,FALSE) | D9: =_xlfn.XLOOKUP(B9,Products!$A$5:$A$12,Products!$C$5:$C$12,"Not found") | E9: 7 | F9: =VLOOKUP(B9,Products!$A$5:$D$12,4,FALSE) | G9: =E9*F9 | H9: =IF(G9>=20,ROUND(G9*5%,2),0) | I9: =G9-H9 | J9: Card
A10: 46301 | B10: P04 | C10: =VLOOKUP(B10,Products!$A$5:$D$12,2,FALSE) | D10: =_xlfn.XLOOKUP(B10,Products!$A$5:$A$12,Products!$C$5:$C$12,"Not found") | E10: 2 | F10: =VLOOKUP(B10,Products!$A$5:$D$12,4,FALSE) | G10: =E10*F10 | H10: =IF(G10>=20,ROUND(G10*5%,2),0) | I10: =G10-H10 | J10: Credit
A11: 46302 | B11: P01 | C11: =VLOOKUP(B11,Products!$A$5:$D$12,2,FALSE) | D11: =_xlfn.XLOOKUP(B11,Products!$A$5:$A$12,Products!$C$5:$C$12,"Not found") | E11: 10 | F11: =VLOOKUP(B11,Products!$A$5:$D$12,4,FALSE) | G11: =E11*F11 | H11: =IF(G11>=20,ROUND(G11*5%,2),0) | I11: =G11-H11 | J11: Cash
A12: 46303 | B12: P04 | C12: =VLOOKUP(B12,Products!$A$5:$D$12,2,FALSE) | D12: =_xlfn.XLOOKUP(B12,Products!$A$5:$A$12,Products!$C$5:$C$12,"Not found") | E12: 11 | F12: =VLOOKUP(B12,Products!$A$5:$D$12,4,FALSE) | G12: =E12*F12 | H12: =IF(G12>=20,ROUND(G12*5%,2),0) | I12: =G12-H12 | J12: Cash
A13: 46304 | B13: P02 | C13: =VLOOKUP(B13,Products!$A$5:$D$12,2,FALSE) | D13: =_xlfn.XLOOKUP(B13,Products!$A$5:$A$12,Products!$C$5:$C$12,"Not found") | E13: 6 | F13: =VLOOKUP(B13,Products!$A$5:$D$12,4,FALSE) | G13: =E13*F13 | H13: =IF(G13>=20,ROUND(G13*5%,2),0) | I13: =G13-H13 | J13: Card
A14: 46305 | B14: P08 | C14: =VLOOKUP(B14,Products!$A$5:$D$12,2,FALSE) | D14: =_xlfn.XLOOKUP(B14,Products!$A$5:$A$12,Products!$C$5:$C$12,"Not found") | E14: 4 | F14: =VLOOKUP(B14,Products!$A$5:$D$12,4,FALSE) | G14: =E14*F14 | H14: =IF(G14>=20,ROUND(G14*5%,2),0) | I14: =G14-H14 | J14: Card
A15: 46306 | B15: P03 | C15: =VLOOKUP(B15,Products!$A$5:$D$12,2,FALSE) | D15: =_xlfn.XLOOKUP(B15,Products!$A$5:$A$12,Products!$C$5:$C$12,"Not found") | E15: 5 | F15: =VLOOKUP(B15,Products!$A$5:$D$12,4,FALSE) | G15: =E15*F15 | H15: =IF(G15>=20,ROUND(G15*5%,2),0) | I15: =G15-H15 | J15: Cash
A16: 46307 | B16: P07 | C16: =VLOOKUP(B16,Products!$A$5:$D$12,2,FALSE) | D16: =_xlfn.XLOOKUP(B16,Products!$A$5:$A$12,Products!$C$5:$C$12,"Not found") | E16: 12 | F16: =VLOOKUP(B16,Products!$A$5:$D$12,4,FALSE) | G16: =E16*F16 | H16: =IF(G16>=20,ROUND(G16*5%,2),0) | I16: =G16-H16 | J16: Card
... A24: 46315 | B24: P08 | C24: =VLOOKUP(B24,Products!$A$5:$D$12,2,FALSE) | D24: =_xlfn.XLOOKUP(B24,Products!$A$5:$A$12,Products!$C$5:$C$12,"Not found") | E24: 7 | F24: =VLOOKUP(B24,Products!$A$5:$D$12,4,FALSE) | G24: =E24*F24 | H24: =IF(G24>=20,ROUND(G24*5%,2),0) | I24: =G24-H24 | J24: Card
G25: =SUM(G5:G24) | H25: =SUM(H5:H24) | I25: =SUM(I5:I24)

Sheet Products
A1: Product List
A2: Change a price here - the Sales sheet updates automatically
A4: Code | B4: Product | C4: Category | D4: Price
A5: P01 | B5: Rice 5kg | C5: Grocery | D5: 8
A6: P02 | B6: Cooking Oil 1L | C6: Grocery | D6: 4.5
A7: P03 | B7: Sugar 2kg | C7: Grocery | D7: 3.2
A8: P04 | B8: Soap (4-pack) | C8: Household | D8: 3
A9: P05 | B9: Detergent 1kg | C9: Household | D9: 5.5
A10: P06 | B10: Biscuits | C10: Snacks | D10: 1
A11: P07 | B11: Potato Chips | C11: Snacks | D11: 1.5
A12: P08 | B12: Coffee 200g | C12: Grocery | D12: 6

Sheet Summary
A1: Summary
A2: Every number here is a formula linked to the Sales sheet
A4: Total net sales | B4: =SUM(Sales!I5:I24)
A5: Average bill | B5: =ROUND(AVERAGE(Sales!I5:I24),2)
A6: Largest bill | B6: =MAX(Sales!I5:I24)
A7: Smallest bill | B7: =MIN(Sales!I5:I24)
A8: Number of bills | B8: =COUNT(Sales!I5:I24)
A9: Card bills | B9: =COUNTIF(Sales!J5:J24,"Card")
A10: Credit (unpaid) bills | B10: =COUNTIF(Sales!J5:J24,"Credit")
A13: Category | B13: Net Sales | C13: Bills | D13: Card Sales
A14: Grocery | B14: =SUMIF(Sales!$D$5:$D$24,A14,Sales!$I$5:$I$24) | C14: =COUNTIF(Sales!$D$5:$D$24,A14) | D14: =SUMIFS(Sales!$I$5:$I$24,Sales!$D$5:$D$24,A14,Sales!$J$5:$J$24,"Card")
A15: Household | B15: =SUMIF(Sales!$D$5:$D$24,A15,Sales!$I$5:$I$24) | C15: =COUNTIF(Sales!$D$5:$D$24,A15) | D15: =SUMIFS(Sales!$I$5:$I$24,Sales!$D$5:$D$24,A15,Sales!$J$5:$J$24,"Card")
A16: Snacks | B16: =SUMIF(Sales!$D$5:$D$24,A16,Sales!$I$5:$I$24) | C16: =COUNTIF(Sales!$D$5:$D$24,A16) | D16: =SUMIFS(Sales!$I$5:$I$24,Sales!$D$5:$D$24,A16,Sales!$J$5:$J$24,"Card")
A17: Total | B17: =SUM(B14:B16) | C17: =SUM(C14:C16) | D17: =SUM(D14:D16)
A19: Grocery + Card bills (COUNTIFS) | B19: =COUNTIFS(Sales!D5:D24,"Grocery",Sales!J5:J24,"Card")
A20: Price of P03 (INDEX+MATCH) | B20: =INDEX(Products!D5:D12,MATCH("P03",Products!A5:A12,0))
A21: Price of P99 (IFERROR) | B21: =IFERROR(VLOOKUP("P99",Products!A5:D12,4,FALSE),"Wrong code")

Sheet Formula_Lab
A1: Formula Lab - text & date formulas
A2: Messy customer data in A-E, clean results in F-L
A4: As-of date | B4: 46311
A7: Name (raw) | B7: Phone | C7: Day | D7: Month | E7: Year | F7: Clean Name | G7: Phone (formatted) | H7: Birth Date | I7: Age (yrs) | J7: Date as text | K7: Customer ID | L7: Eligible?
A8: maria santos | B8: 5551234567 | C8: 5 | D8: 3 | E8: 1998 | F8: =PROPER(TRIM(A8)) | G8: =LEFT(B8,3)&"-"&MID(B8,4,3)&"-"&RIGHT(B8,4) | H8: =DATE(E8,D8,C8) | I8: =DATEDIF(H8,$B$4,"y") | J8: =TEXT(H8,"dd mmm yyyy") | K8: ="C-"&UPPER(LEFT(F8,2))&RIGHT(B8,4) | L8: =IF(AND(I8>=18,LEN(B8)=10),"Yes","No")
A9: JOHN okafor | B9: 5559876543 | C9: 21 | D9: 11 | E9: 2009 | F9: =PROPER(TRIM(A9)) | G9: =LEFT(B9,3)&"-"&MID(B9,4,3)&"-"&RIGHT(B9,4) | H9: =DATE(E9,D9,C9) | I9: =DATEDIF(H9,$B$4,"y") | J9: =TEXT(H9,"dd mmm yyyy") | K9: ="C-"&UPPER(LEFT(F9,2))&RIGHT(B9,4) | L9: =IF(AND(I9>=18,LEN(B9)=10),"Yes","No")
A10: aisha khan | B10: 555 246 8101 | C10: 14 | D10: 7 | E10: 1985 | F10: =PROPER(TRIM(A10)) | G10: =LEFT(B10,3)&"-"&MID(B10,4,3)&"-"&RIGHT(B10,4) | H10: =DATE(E10,D10,C10) | I10: =DATEDIF(H10,$B$4,"y") | J10: =TEXT(H10,"dd mmm yyyy") | K10: ="C-"&UPPER(LEFT(F10,2))&RIGHT(B10,4) | L10: =IF(AND(I10>=18,LEN(B10)=10),"Yes","No")
A11: david LEE | B11: 5551357913 | C11: 2 | D11: 1 | E11: 2004 | F11: =PROPER(TRIM(A11)) | G11: =LEFT(B11,3)&"-"&MID(B11,4,3)&"-"&RIGHT(B11,4) | H11: =DATE(E11,D11,C11) | I11: =DATEDIF(H11,$B$4,"y") | J11: =TEXT(H11,"dd mmm yyyy") | K11: ="C-"&UPPER(LEFT(F11,2))&RIGHT(B11,4) | L11: =IF(AND(I11>=18,LEN(B11)=10),"Yes","No")
